CHANGES.txt
README.txt
bootstrap.py
buildout.cfg
setup.py
src/zope/__init__.py
src/zope.app.module.egg-info/PKG-INFO
src/zope.app.module.egg-info/SOURCES.txt
src/zope.app.module.egg-info/dependency_links.txt
src/zope.app.module.egg-info/namespace_packages.txt
src/zope.app.module.egg-info/not-zip-safe
src/zope.app.module.egg-info/requires.txt
src/zope.app.module.egg-info/top_level.txt
src/zope/app/__init__.py
src/zope/app/module/PACKAGE.cfg
src/zope/app/module/README.txt
src/zope/app/module/__init__.py
src/zope/app/module/configure.zcml
src/zope/app/module/interfaces.py
src/zope/app/module/interfaces.txt
src/zope/app/module/manager.py
src/zope/app/module/tests.py
src/zope/app/module/browser/__init__.py
src/zope/app/module/browser/browse_module.pt
src/zope/app/module/browser/configure.zcml